pdftty/__init__.py
pdftty/ansi_widget.py
pdftty/controller.py
pdftty/main.py
pdftty/model.py
pdftty/pdf_handling.py
pdftty/renderer.py
pdftty/view.py
pdftty-0.0.2.dist-info/entry_points.txt
pdftty-0.0.2.dist-info/WHEEL
pdftty-0.0.2.dist-info/METADATA
pdftty-0.0.2.dist-info/RECORD
